pi_query_tool/PreProcessor.py
pi_query_tool/Querry.py
pi_query_tool/__init__.py
pi_db_query-1.0.2.dist-info/METADATA
pi_db_query-1.0.2.dist-info/WHEEL
pi_db_query-1.0.2.dist-info/top_level.txt
pi_db_query-1.0.2.dist-info/RECORD
